{
    "index": "0572",
    "prev": "0571",
    "next": "0573",
    "title": "Garfildo antaŭĝojas pri Kristnasko",
    "date": "2003-12-24",
    "version": 0,
    "sunday": "false",
    "image_bytes": 1479816,
    "errata": [],
    "props": {
        "nogarfield": false,
        "notext": false,
        "good": false,
        "earsback": false
    },
    "transcript": [
        [
            ["GARFILDO", "Estas Kristnaskvespere... donacoj estas pakitaj, ĥoraĵoj kantitaj, kaj la manĝetoj por Sankta Nikolao atendas"]
        ],
        [
            ["GARFILDO", "Estas nur unu ago farota..."]
        ],
        [
            ["GARFILDO", "-Ne kapabli ekdormi la tutan nokton"]
        ]
    ],
    "special": "kristnasko",
    "is_old": false
}